from_notebook/__init__.py
from_notebook/_import_hook.py
from_notebook-1.0.0.dist-info/LICENSE
from_notebook-1.0.0.dist-info/METADATA
from_notebook-1.0.0.dist-info/WHEEL
from_notebook-1.0.0.dist-info/top_level.txt
from_notebook-1.0.0.dist-info/RECORD
