Metadata-Version: 2.1
Name: from-notebook
Version: 1.0.0
Summary: Small Python utility for importing functions, classes, and constants from .ipynb files.
Home-page: https://github.com/wootfish/from_notebook
Author: Eli Sohl
Author-email: elisohl@gmail.com
License: MIT
Platform: UNKNOWN
